.scrutinizer.yml
LICENSE.txt
MANIFEST.in
setup.cfg
setup.py
sherbet.py
Sherbet.egg-info/PKG-INFO
Sherbet.egg-info/SOURCES.txt
Sherbet.egg-info/dependency_links.txt
Sherbet.egg-info/top_level.txt
test/__init__.py
test/test_expression.py
test/test_sherbet.py