Metadata-Version: 1.0
Name: Sherbet
Version: 0.1.1
Summary: Sherbet library automates word inflection to support plurals
Home-page: https://github.com/vasili-v/sherbet
Author: Vasili Vasilyeu
Author-email: vasili.v@tut.by
License: MIT
Platform: Darwin
Platform: Linux
